cell_ann/__init__.py
cell_ann/__version__.py
cell_ann/_knn.py
cell_ann/_logger.py
cell_ann/_core/__init__.py
cell_ann/_core/_base_knn.py
cell_ann/_core/_neighbor_query.py
cell_ann/_core/_query_mapper.py
cell_ann/_core/_self_id_mix_in.py
cell_ann/_core/_type_check_mix_in.py
cell_ann/_core/_value_counts_assignment.py
cell_ann-0.0.1.dist-info/LICENSE
cell_ann-0.0.1.dist-info/METADATA
cell_ann-0.0.1.dist-info/WHEEL
cell_ann-0.0.1.dist-info/top_level.txt
cell_ann-0.0.1.dist-info/RECORD
